pdtools/__init__.py
pdtools/__main__.py
pdtools/authenticated_client.py
pdtools/chute.py
pdtools/cloud.py
pdtools/comm.py
pdtools/config.py
pdtools/controller_client.py
pdtools/device.py
pdtools/discover.py
pdtools/errors.py
pdtools/groups.py
pdtools/node.py
pdtools/paradrop_client.py
pdtools/routers.py
pdtools/server.py
pdtools/store.py
pdtools/token_provider.py
pdtools/util.py
pdtools/wizard.py
pdtools/devices/__init__.py
pdtools/devices/camera.py
pdtools/helpers/__init__.py
pdtools/helpers/chute.py
pdtools/schemas/chute.json
pdtools-0.13.2.dist-info/METADATA
pdtools-0.13.2.dist-info/WHEEL
pdtools-0.13.2.dist-info/entry_points.txt
pdtools-0.13.2.dist-info/top_level.txt
pdtools-0.13.2.dist-info/RECORD
