Metadata-Version: 2.1
Name: pdtools
Version: 0.13.2
Summary: Paradrop Developer Tools
Home-page: https://paradrop.org
Maintainer: Lance Hartung
Maintainer-email: lance@paradrop.io
License: UNKNOWN
Project-URL: Source, https://github.com/ParadropLabs/Paradrop
Project-URL: Documentation, https://paradrop.readthedocs.io/en/latest/
Project-URL: Homepage, https://paradrop.org
Platform: UNKNOWN
Classifier: Development Status :: 4 - Beta
Classifier: Environment :: Console
Classifier: Intended Audience :: Developers
Classifier: Intended Audience :: System Administrators
Classifier: License :: OSI Approved :: Apache Software License
Classifier: Operating System :: OS Independent
Classifier: Programming Language :: Python :: 2
Classifier: Programming Language :: Python :: 2.7
Classifier: Programming Language :: Python :: 3
Classifier: Topic :: Software Development
Classifier: Topic :: Utilities
Requires-Python: >=2.7
Requires-Dist: appdirs (~=1.4.3)
Requires-Dist: arrow (~=0.10.0)
Requires-Dist: click (~=6.7)
Requires-Dist: future (~=0.16.0)
Requires-Dist: GitPython (~=2.1.5)
Requires-Dist: jsonschema (~=2.6.0)
Requires-Dist: PyYAML (~=5.1)
Requires-Dist: requests (>=2.21.0)
Requires-Dist: six (~=1.10.0)
Requires-Dist: websocket-client (~=0.40.0)
